learnkit/__init__.py
learnkit-0.0.0.dist-info/METADATA
learnkit-0.0.0.dist-info/WHEEL
learnkit-0.0.0.dist-info/licenses/LICENSE.txt
learnkit-0.0.0.dist-info/RECORD
